MANIFEST.in
README.txt
setup.py
docs/HISTORY.txt
docs/LICENSE.GPL
docs/LICENSE.txt
mfabrik/__init__.py
mfabrik.zoho.egg-info/PKG-INFO
mfabrik.zoho.egg-info/SOURCES.txt
mfabrik.zoho.egg-info/dependency_links.txt
mfabrik.zoho.egg-info/entry_points.txt
mfabrik.zoho.egg-info/namespace_packages.txt
mfabrik.zoho.egg-info/not-zip-safe
mfabrik.zoho.egg-info/requires.txt
mfabrik.zoho.egg-info/top_level.txt
mfabrik/zoho/__init__.py
mfabrik/zoho/core.py
mfabrik/zoho/crm.py
mfabrik/zoho/tests.py