Metadata-Version: 1.0
Name: mfabrik.zoho
Version: 1.1
Summary: Zoho API integration for Python
Home-page: http://github.com/miohtama/mfabrik.zoho
Author: mFabrik Research Oy
Author-email: info@mfabrik.com
License: GPL
Keywords: zoho api developers crm
Platform: UNKNOWN
Classifier: Programming Language :: Python
